{"images/background.jpg":["images/background.jpg"],"images/bottlecap_0.png":["images/bottlecap_0.png"],"images/bottlecap_1.png":["images/bottlecap_1.png"],"images/bottlecap_10.png":["images/bottlecap_10.png"],"images/bottlecap_2.png":["images/bottlecap_2.png"],"images/bottlecap_3.png":["images/bottlecap_3.png"],"images/bottlecap_4.png":["images/bottlecap_4.png"],"images/bottlecap_5.png":["images/bottlecap_5.png"],"images/bottlecap_6.png":["images/bottlecap_6.png"],"images/bottlecap_7.png":["images/bottlecap_7.png"],"images/bottlecap_8.png":["images/bottlecap_8.png"],"images/bottlecap_9.png":["images/bottlecap_9.png"]}